<menus version="1">	<menu name="Colors" kind="color">		<item name="normal"/>		<separator/>		<item name="base1"/>		<item name="base0"/>		<item name="base01"/>			<item name="base02"/>		<item name="base03"/>		<separator/>		<item name="base01"/>		<item name="base00"/>		<item name="base1"/>			<item name="base2"/>		<item name="base3"/>		<separator/>		<item name="blue"/>		<item name="cyan"/>		<item name="green"/>		<item name="magenta"/>		<item name="orange"/>		<item name="poppy" />		<item name="red"/>		<item name="violet"/>				<item name="yellow"/>			</menu>	<menu name="Value" kind="stamps">	</menu></menus>